<?xml version="1.0" encoding="utf-8" ?>
<hibernate-mapping xmlns="urn:nhibernate-mapping-2.2"
                   assembly="RMIS.Entities.BackEnd"
                   namespace="RMIS.Entities.BackEnd">

  <class name="DustStockInfo" table="[dbo].[DustStockInfo]" optimistic-lock="none" >
    <id name="DustStockID" column="DustStockID" >
      <generator class="assigned"/>
    </id>
    <property name="CustID" column="CustID" />
    <property name="TotalBags" column="TotalBags" />
    <property name="UnitsTypeID" column="UnitsTypeID" />
    <property name="ObsInd" column="ObsInd" />
    <property name="LastModifiedBy" column="LastModifiedBy" />
    <property name="LastModifiedDate" column="LastModifiedDate" />

  </class>
</hibernate-mapping>

